KenkoAdvance/AyDict.py
KenkoAdvance/AyStr.py
KenkoAdvance/Base64.py
KenkoAdvance/GocqConnection.py
KenkoAdvance/HiddenPrints.py
KenkoAdvance/TextToMidi.py
KenkoAdvance/__init__.py
KenkoAdvance/get_file_format.py
KenkoAdvance/int_to_chinese.py
KenkoAdvance/single_functions.py
KenkoAdvance/AyAdb/App.py
KenkoAdvance/AyAdb/Files.py
KenkoAdvance/AyAdb/Images.py
KenkoAdvance/AyAdb/Info.py
KenkoAdvance/AyAdb/Settings.py
KenkoAdvance/AyAdb/Touch.py
KenkoAdvance/AyAdb/__init__.py
KenkoAdvance/AyAdb/adb_command.py
KenkoAdvance-1.0.0.dist-info/LICENSE
KenkoAdvance-1.0.0.dist-info/METADATA
KenkoAdvance-1.0.0.dist-info/WHEEL
KenkoAdvance-1.0.0.dist-info/top_level.txt
KenkoAdvance-1.0.0.dist-info/RECORD
