Metadata-Version: 2.1
Name: KenkoAdvance
Version: 1.0.0
Summary: 自用的一些功能
Home-page: https://github.com/AkagiYui/KenkoAdvance
Author: AkagiYui
Author-email: akagiyui@yeah.net
License: MIT
Platform: UNKNOWN
Classifier: Programming Language :: Python :: 3
Classifier: License :: OSI Approved :: MIT License
Classifier: Operating System :: OS Independent
Requires-Python: >=3.9
License-File: LICENSE
